[
  {
    "op": "8C",
    "offset": 0,
    "value": [
      "u16:114",
      "u8:0"
    ]
  },
  {
    "op": "03",
    "offset": 4,
    "value": [
      "u8:2",
      "u16:21",
      "u8:0",
      "u16:3",
      "u8:0"
    ]
  },
  {
    "op": "01",
    "offset": 12,
    "value": [
      "u8:6",
      "u16:21",
      "u16:0",
      "u32:8",
      "u8:0"
    ]
  },
  {
    "op": "03",
    "offset": 23,
    "value": [
      "u8:1",
      "u16:21",
      "u8:0",
      "u16:0",
      "u8:0"
    ]
  },
  {
    "op": "03",
    "offset": 31,
    "value": [
      "u8:2",
      "u16:23",
      "u8:0",
      "u16:2",
      "u8:0"
    ]
  },
  {
    "op": "01",
    "offset": 39,
    "value": [
      "u8:6",
      "u16:23",
      "u16:0",
      "u32:8",
      "u8:0"
    ]
  },
  {
    "op": "03",
    "offset": 50,
    "value": [
      "u8:1",
      "u16:23",
      "u8:0",
      "u16:0",
      "u8:0"
    ]
  },
  {
    "op": "03",
    "offset": 58,
    "value": [
      "u8:1",
      "u16:13",
      "u8:0",
      "u16:2",
      "u8:0"
    ]
  },
  {
    "op": "26",
    "offset": 66,
    "value": [
      "u16:0"
    ]
  },
  {
    "op": "49",
    "offset": 69,
    "value": [
      "u8:0",
      "u8:0",
      "u8:0"
    ]
  },
  {
    "op": "49",
    "offset": 73,
    "value": [
      "u8:1",
      "u8:0",
      "u8:0"
    ]
  },
  {
    "op": "46",
    "offset": 77,
    "value": [
      "u16:0",
      "u16:0",
      "u32:0",
      "u8:0",
      "BLACK"
    ]
  },
  {
    "op": "4A",
    "offset": 93,
    "value": [
      "bytes:19 E8 03 00"
    ]
  },
  {
    "op": "21",
    "offset": 98,
    "value": [
      "u8:0",
      "u16:0",
      "BGM03"
    ]
  },
  {
    "op": "49",
    "offset": 108,
    "value": [
      "u8:0",
      "u8:0",
      "u8:0"
    ]
  },
  {
    "op": "49",
    "offset": 112,
    "value": [
      "u8:1",
      "u8:0",
      "u8:0"
    ]
  },
  {
    "op": "46",
    "offset": 116,
    "value": [
      "u16:0",
      "u16:0",
      "u32:0",
      "u8:0",
      "B241"
    ]
  },
  {
    "op": "48",
    "offset": 131,
    "value": [
      "u8:1",
      "u16:198",
      "u16:0",
      "u32:0",
      "u8:0",
      "a120_2c"
    ]
  },
  {
    "op": "4A",
    "offset": 150,
    "value": [
      "bytes:19 E8 03 00"
    ]
  },
  {
    "op": "41",
    "offset": 155,
    "value": [
      "u16:0",
      "u8:0",
      "　思わずどきりとした。"
    ]
  },
  {
    "op": "41",
    "offset": 182,
    "value": [
      "u16:1",
      "u8:0",
      "　おれの大好きなあの服で──あの大胆な服で、エレナさん\\nが迎えに来てくれた。"
    ]
  },
  {
    "op": "41",
    "offset": 263,
    "value": [
      "u16:2",
      "u8:0",
      "　それも、わざわざホームまで。"
    ]
  },
  {
    "op": "23",
    "offset": 298,
    "value": [
      "u8:0",
      "u16:65535",
      "u16:0",
      "ele_0769.ogg"
    ]
  },
  {
    "op": "42",
    "offset": 317,
    "value": [
      "u16:3",
      "u8:0",
      "u8:0",
      "エレナ",
      "「違う服の方が、よかった？」"
    ]
  },
  {
    "op": "42",
    "offset": 358,
    "value": [
      "u16:4",
      "u8:0",
      "u8:0",
      "花丸",
      "「ううん……凄くいい」"
    ]
  },
  {
    "op": "41",
    "offset": 391,
    "value": [
      "u16:5",
      "u8:0",
      "　思わず見つめてしまう。"
    ]
  },
  {
    "op": "41",
    "offset": 420,
    "value": [
      "u16:6",
      "u8:0",
      "　──そうだ。ルナのことだったんだ。"
    ]
  },
  {
    "op": "42",
    "offset": 461,
    "value": [
      "u16:7",
      "u8:0",
      "u8:0",
      "花丸",
      "「ちょっと従妹の様子見てきていい？」"
    ]
  },
  {
    "op": "49",
    "offset": 508,
    "value": [
      "u8:0",
      "u8:0",
      "u8:0"
    ]
  },
  {
    "op": "49",
    "offset": 512,
    "value": [
      "u8:1",
      "u8:0",
      "u8:0"
    ]
  },
  {
    "op": "46",
    "offset": 516,
    "value": [
      "u16:0",
      "u16:0",
      "u32:0",
      "u8:0",
      "B241"
    ]
  },
  {
    "op": "48",
    "offset": 531,
    "value": [
      "u8:1",
      "u16:198",
      "u16:0",
      "u32:0",
      "u8:0",
      "a120_00"
    ]
  },
  {
    "op": "4A",
    "offset": 550,
    "value": [
      "bytes:19 F4 01 00"
    ]
  },
  {
    "op": "23",
    "offset": 555,
    "value": [
      "u8:0",
      "u16:65535",
      "u16:0",
      "ele_0770.ogg"
    ]
  },
  {
    "op": "42",
    "offset": 574,
    "value": [
      "u16:8",
      "u8:0",
      "u8:0",
      "エレナ",
      "「従妹？」"
    ]
  },
  {
    "op": "42",
    "offset": 597,
    "value": [
      "u16:9",
      "u8:0",
      "u8:0",
      "花丸",
      "「なんか、変質者がうろついてるみたいなんだ。マンション\\n　の近く」"
    ]
  },
  {
    "op": "49",
    "offset": 674,
    "value": [
      "u8:0",
      "u8:0",
      "u8:0"
    ]
  },
  {
    "op": "49",
    "offset": 678,
    "value": [
      "u8:1",
      "u8:0",
      "u8:0"
    ]
  },
  {
    "op": "46",
    "offset": 682,
    "value": [
      "u16:0",
      "u16:0",
      "u32:0",
      "u8:0",
      "B241"
    ]
  },
  {
    "op": "48",
    "offset": 697,
    "value": [
      "u8:1",
      "u16:198",
      "u16:0",
      "u32:0",
      "u8:0",
      "a120_1d"
    ]
  },
  {
    "op": "4A",
    "offset": 716,
    "value": [
      "bytes:19 F4 01 00"
    ]
  },
  {
    "op": "23",
    "offset": 721,
    "value": [
      "u8:0",
      "u16:65535",
      "u16:0",
      "ele_0771.ogg"
    ]
  },
  {
    "op": "42",
    "offset": 740,
    "value": [
      "u16:10",
      "u8:0",
      "u8:0",
      "エレナ",
      "「変質者？」"
    ]
  },
  {
    "op": "42",
    "offset": 765,
    "value": [
      "u16:11",
      "u8:0",
      "u8:0",
      "花丸",
      "「うん。エレナさんの後にすぐ電話あって」"
    ]
  },
  {
    "op": "49",
    "offset": 816,
    "value": [
      "u8:0",
      "u8:0",
      "u8:0"
    ]
  },
  {
    "op": "49",
    "offset": 820,
    "value": [
      "u8:1",
      "u8:0",
      "u8:0"
    ]
  },
  {
    "op": "46",
    "offset": 824,
    "value": [
      "u16:0",
      "u16:0",
      "u32:0",
      "u8:0",
      "B241"
    ]
  },
  {
    "op": "48",
    "offset": 839,
    "value": [
      "u8:1",
      "u16:198",
      "u16:0",
      "u32:0",
      "u8:0",
      "a120_00"
    ]
  },
  {
    "op": "4A",
    "offset": 858,
    "value": [
      "bytes:19 F4 01 00"
    ]
  },
  {
    "op": "23",
    "offset": 863,
    "value": [
      "u8:0",
      "u16:65535",
      "u16:0",
      "ele_0772.ogg"
    ]
  },
  {
    "op": "42",
    "offset": 882,
    "value": [
      "u16:12",
      "u8:0",
      "u8:0",
      "エレナ",
      "「──いいわ。わたしもいっしょに行くわ」"
    ]
  },
  {
    "op": "42",
    "offset": 935,
    "value": [
      "u16:13",
      "u8:0",
      "u8:0",
      "花丸",
      "「え？」"
    ]
  },
  {
    "op": "23",
    "offset": 954,
    "value": [
      "u8:0",
      "u16:65535",
      "u16:0",
      "ele_0773.ogg"
    ]
  },
  {
    "op": "42",
    "offset": 973,
    "value": [
      "u16:14",
      "u8:0",
      "u8:0",
      "エレナ",
      "「花丸くん一人じゃ心配だし」"
    ]
  },
  {
    "op": "49",
    "offset": 1014,
    "value": [
      "u8:0",
      "u8:0",
      "u8:0"
    ]
  },
  {
    "op": "49",
    "offset": 1018,
    "value": [
      "u8:1",
      "u8:0",
      "u8:0"
    ]
  },
  {
    "op": "46",
    "offset": 1022,
    "value": [
      "u16:0",
      "u16:0",
      "u32:0",
      "u8:0",
      "B241"
    ]
  },
  {
    "op": "48",
    "offset": 1037,
    "value": [
      "u8:1",
      "u16:198",
      "u16:0",
      "u32:0",
      "u8:0",
      "a120_2c"
    ]
  },
  {
    "op": "4A",
    "offset": 1056,
    "value": [
      "bytes:19 F4 01 00"
    ]
  },
  {
    "op": "42",
    "offset": 1061,
    "value": [
      "u16:15",
      "u8:0",
      "u8:0",
      "花丸",
      "「それ、どういう意味？」"
    ]
  },
  {
    "op": "23",
    "offset": 1096,
    "value": [
      "u8:0",
      "u16:65535",
      "u16:0",
      "ele_0774.ogg"
    ]
  },
  {
    "op": "42",
    "offset": 1115,
    "value": [
      "u16:16",
      "u8:0",
      "u8:0",
      "エレナ",
      "「早く行きましょ」"
    ]
  },
  {
    "op": "22",
    "offset": 1146,
    "value": [
      "u8:1",
      "u16:1000",
      "u8:0"
    ]
  },
  {
    "op": "49",
    "offset": 1151,
    "value": [
      "u8:0",
      "u8:0",
      "u8:0"
    ]
  },
  {
    "op": "49",
    "offset": 1155,
    "value": [
      "u8:1",
      "u8:0",
      "u8:0"
    ]
  },
  {
    "op": "46",
    "offset": 1159,
    "value": [
      "u16:0",
      "u16:0",
      "u32:0",
      "u8:0",
      "BLACK"
    ]
  },
  {
    "op": "4A",
    "offset": 1175,
    "value": [
      "bytes:19 E8 03 00"
    ]
  },
  {
    "op": "41",
    "offset": 1180,
    "value": [
      "u16:17",
      "u8:0",
      "　事前に電話しておいたからか、ルナはすぐに開けてくれた。"
    ]
  },
  {
    "op": "21",
    "offset": 1241,
    "value": [
      "u8:0",
      "u16:0",
      "BGM14"
    ]
  },
  {
    "op": "49",
    "offset": 1251,
    "value": [
      "u8:0",
      "u8:0",
      "u8:0"
    ]
  },
  {
    "op": "49",
    "offset": 1255,
    "value": [
      "u8:1",
      "u8:0",
      "u8:0"
    ]
  },
  {
    "op": "46",
    "offset": 1259,
    "value": [
      "u16:0",
      "u16:0",
      "u32:0",
      "u8:0",
      "B020BL"
    ]
  },
  {
    "op": "48",
    "offset": 1276,
    "value": [
      "u8:1",
      "u16:212",
      "u16:0",
      "u32:0",
      "u8:0",
      "a212_1d"
    ]
  },
  {
    "op": "4A",
    "offset": 1295,
    "value": [
      "bytes:19 E8 03 00"
    ]
  },
  {
    "op": "23",
    "offset": 1300,
    "value": [
      "u8:0",
      "u16:65535",
      "u16:0",
      "lun_0290.ogg"
    ]
  },
  {
    "op": "42",
    "offset": 1319,
    "value": [
      "u16:18",
      "u8:0",
      "u8:0",
      "ルナ",
      "「あ……」"
    ]
  },
  {
    "op": "23",
    "offset": 1340,
    "value": [
      "u8:0",
      "u16:65535",
      "u16:0",
      "ele_0775.ogg"
    ]
  },
  {
    "op": "42",
    "offset": 1359,
    "value": [
      "u16:19",
      "u8:0",
      "u8:0",
      "エレナ",
      "「初めまして」"
    ]
  },
  {
    "op": "23",
    "offset": 1386,
    "value": [
      "u8:0",
      "u16:65535",
      "u16:0",
      "lun_0291.ogg"
    ]
  },
  {
    "op": "42",
    "offset": 1405,
    "value": [
      "u16:20",
      "u8:0",
      "u8:0",
      "ルナ",
      "「あ……こちらこそ初めまして。鮎川です……」"
    ]
  },
  {
    "op": "23",
    "offset": 1460,
    "value": [
      "u8:0",
      "u16:65535",
      "u16:0",
      "ele_0776.ogg"
    ]
  },
  {
    "op": "42",
    "offset": 1479,
    "value": [
      "u16:21",
      "u8:0",
      "u8:0",
      "エレナ",
      "「北条です」"
    ]
  },
  {
    "op": "41",
    "offset": 1504,
    "value": [
      "u16:22",
      "u8:0",
      "　おれの知っている女性が丁寧語で挨拶をかわすというのは、\\n妙な感じがするものだ。"
    ]
  },
  {
    "op": "42",
    "offset": 1589,
    "value": [
      "u16:23",
      "u8:0",
      "u8:0",
      "花丸",
      "「変質者は出たか？」"
    ]
  },
  {
    "op": "49",
    "offset": 1620,
    "value": [
      "u8:0",
      "u8:0",
      "u8:0"
    ]
  },
  {
    "op": "49",
    "offset": 1624,
    "value": [
      "u8:1",
      "u8:0",
      "u8:0"
    ]
  },
  {
    "op": "46",
    "offset": 1628,
    "value": [
      "u16:0",
      "u16:0",
      "u32:0",
      "u8:0",
      "B020BL"
    ]
  },
  {
    "op": "48",
    "offset": 1645,
    "value": [
      "u8:1",
      "u16:212",
      "u16:0",
      "u32:0",
      "u8:0",
      "a212_1b"
    ]
  },
  {
    "op": "4A",
    "offset": 1664,
    "value": [
      "bytes:19 F4 01 00"
    ]
  },
  {
    "op": "23",
    "offset": 1669,
    "value": [
      "u8:0",
      "u16:65535",
      "u16:0",
      "lun_0292.ogg"
    ]
  },
  {
    "op": "42",
    "offset": 1688,
    "value": [
      "u16:24",
      "u8:0",
      "u8:0",
      "ルナ",
      "「ううん……ごめんね。お兄ちゃん、デートの途中だったん\\n　でしょ？」"
    ]
  },
  {
    "op": "42",
    "offset": 1767,
    "value": [
      "u16:25",
      "u8:0",
      "u8:0",
      "花丸",
      "「いや。出かけるところだったんだ」"
    ]
  },
  {
    "op": "23",
    "offset": 1812,
    "value": [
      "u8:0",
      "u16:65535",
      "u16:0",
      "lun_0293.ogg"
    ]
  },
  {
    "op": "42",
    "offset": 1831,
    "value": [
      "u16:26",
      "u8:0",
      "u8:0",
      "ルナ",
      "「ごめんね」"
    ]
  },
  {
    "op": "42",
    "offset": 1854,
    "value": [
      "u16:27",
      "u8:0",
      "u8:0",
      "花丸",
      "「いいよ。ランプってどこでしたんだ？」"
    ]
  },
  {
    "op": "23",
    "offset": 1903,
    "value": [
      "u8:0",
      "u16:65535",
      "u16:0",
      "lun_0294.ogg"
    ]
  },
  {
    "op": "42",
    "offset": 1922,
    "value": [
      "u16:28",
      "u8:0",
      "u8:0",
      "ルナ",
      "「あっち」"
    ]
  },
  {
    "op": "49",
    "offset": 1943,
    "value": [
      "u8:0",
      "u8:0",
      "u8:0"
    ]
  },
  {
    "op": "49",
    "offset": 1947,
    "value": [
      "u8:1",
      "u8:0",
      "u8:0"
    ]
  },
  {
    "op": "46",
    "offset": 1951,
    "value": [
      "u16:0",
      "u16:0",
      "u32:0",
      "u8:0",
      "B022BL"
    ]
  },
  {
    "op": "4A",
    "offset": 1968,
    "value": [
      "bytes:19 F4 01 00"
    ]
  },
  {
    "op": "41",
    "offset": 1973,
    "value": [
      "u16:29",
      "u8:0",
      "　ルナに言われた方を見る。人らしき姿は見えない。"
    ]
  },
  {
    "op": "49",
    "offset": 2026,
    "value": [
      "u8:0",
      "u8:0",
      "u8:0"
    ]
  },
  {
    "op": "49",
    "offset": 2030,
    "value": [
      "u8:1",
      "u8:0",
      "u8:0"
    ]
  },
  {
    "op": "46",
    "offset": 2034,
    "value": [
      "u16:0",
      "u16:0",
      "u32:0",
      "u8:0",
      "B020BL"
    ]
  },
  {
    "op": "48",
    "offset": 2051,
    "value": [
      "u8:1",
      "u16:198",
      "u16:0",
      "u32:0",
      "u8:0",
      "a120_00"
    ]
  },
  {
    "op": "4A",
    "offset": 2070,
    "value": [
      "bytes:19 F4 01 00"
    ]
  },
  {
    "op": "23",
    "offset": 2075,
    "value": [
      "u8:0",
      "u16:65535",
      "u16:0",
      "ele_0777.ogg"
    ]
  },
  {
    "op": "42",
    "offset": 2094,
    "value": [
      "u16:30",
      "u8:0",
      "u8:0",
      "エレナ",
      "「今日は出ないんじゃない？」"
    ]
  },
  {
    "op": "49",
    "offset": 2135,
    "value": [
      "u8:0",
      "u8:0",
      "u8:0"
    ]
  },
  {
    "op": "49",
    "offset": 2139,
    "value": [
      "u8:1",
      "u8:0",
      "u8:0"
    ]
  },
  {
    "op": "46",
    "offset": 2143,
    "value": [
      "u16:0",
      "u16:0",
      "u32:0",
      "u8:0",
      "B020BL"
    ]
  },
  {
    "op": "48",
    "offset": 2160,
    "value": [
      "u8:1",
      "u16:212",
      "u16:0",
      "u32:0",
      "u8:0",
      "a212_1b"
    ]
  },
  {
    "op": "4A",
    "offset": 2179,
    "value": [
      "bytes:19 F4 01 00"
    ]
  },
  {
    "op": "23",
    "offset": 2184,
    "value": [
      "u8:0",
      "u16:65535",
      "u16:0",
      "lun_0295.ogg"
    ]
  },
  {
    "op": "42",
    "offset": 2203,
    "value": [
      "u16:31",
      "u8:0",
      "u8:0",
      "ルナ",
      "「多分、もう出ないと思います。──お兄ちゃん、ほんとご\\n　めんね」"
    ]
  },
  {
    "op": "41",
    "offset": 2280,
    "value": [
      "u16:32",
      "u8:0",
      "　ルナは申し訳なさそうな顔をした。"
    ]
  },
  {
    "op": "23",
    "offset": 2319,
    "value": [
      "u8:0",
      "u16:65535",
      "u16:0",
      "ele_0778.ogg"
    ]
  },
  {
    "op": "42",
    "offset": 2338,
    "value": [
      "u16:33",
      "u8:0",
      "u8:0",
      "エレナ",
      "「行こっか」"
    ]
  },
  {
    "op": "42",
    "offset": 2363,
    "value": [
      "u16:34",
      "u8:0",
      "u8:0",
      "花丸",
      "「うん。……大丈夫か？」"
    ]
  },
  {
    "op": "49",
    "offset": 2398,
    "value": [
      "u8:0",
      "u8:0",
      "u8:0"
    ]
  },
  {
    "op": "49",
    "offset": 2402,
    "value": [
      "u8:1",
      "u8:0",
      "u8:0"
    ]
  },
  {
    "op": "46",
    "offset": 2406,
    "value": [
      "u16:0",
      "u16:0",
      "u32:0",
      "u8:0",
      "B020BL"
    ]
  },
  {
    "op": "48",
    "offset": 2423,
    "value": [
      "u8:1",
      "u16:212",
      "u16:0",
      "u32:0",
      "u8:0",
      "a212_1c"
    ]
  },
  {
    "op": "4A",
    "offset": 2442,
    "value": [
      "bytes:19 F4 01 00"
    ]
  },
  {
    "op": "23",
    "offset": 2447,
    "value": [
      "u8:0",
      "u16:65535",
      "u16:0",
      "lun_0296.ogg"
    ]
  },
  {
    "op": "42",
    "offset": 2466,
    "value": [
      "u16:35",
      "u8:0",
      "u8:0",
      "ルナ",
      "「うん、平気」"
    ]
  },
  {
    "op": "42",
    "offset": 2491,
    "value": [
      "u16:36",
      "u8:0",
      "u8:0",
      "花丸",
      "「変なやつ来ても、ドア開けるなよ。ちゃんとチェーンしと\\n　けよ」"
    ]
  },
  {
    "op": "23",
    "offset": 2566,
    "value": [
      "u8:0",
      "u16:65535",
      "u16:0",
      "lun_0297.ogg"
    ]
  },
  {
    "op": "42",
    "offset": 2585,
    "value": [
      "u16:37",
      "u8:0",
      "u8:0",
      "ルナ",
      "「うん」"
    ]
  },
  {
    "op": "22",
    "offset": 2604,
    "value": [
      "u8:1",
      "u16:1000",
      "u8:0"
    ]
  },
  {
    "op": "49",
    "offset": 2609,
    "value": [
      "u8:0",
      "u8:0",
      "u8:0"
    ]
  },
  {
    "op": "49",
    "offset": 2613,
    "value": [
      "u8:1",
      "u8:0",
      "u8:0"
    ]
  },
  {
    "op": "46",
    "offset": 2617,
    "value": [
      "u16:0",
      "u16:0",
      "u32:0",
      "u8:0",
      "BLACK"
    ]
  },
  {
    "op": "4A",
    "offset": 2633,
    "value": [
      "bytes:19 E8 03 00"
    ]
  },
  {
    "op": "41",
    "offset": 2638,
    "value": [
      "u16:38",
      "u8:0",
      "　見送るというルナを、危ないからと押し止めてマンション\\nを後にした。"
    ]
  },
  {
    "op": "21",
    "offset": 2711,
    "value": [
      "u8:0",
      "u16:0",
      "BGM03"
    ]
  },
  {
    "op": "49",
    "offset": 2721,
    "value": [
      "u8:0",
      "u8:0",
      "u8:0"
    ]
  },
  {
    "op": "49",
    "offset": 2725,
    "value": [
      "u8:1",
      "u8:0",
      "u8:0"
    ]
  },
  {
    "op": "46",
    "offset": 2729,
    "value": [
      "u16:0",
      "u16:0",
      "u32:0",
      "u8:0",
      "B241"
    ]
  },
  {
    "op": "48",
    "offset": 2744,
    "value": [
      "u8:1",
      "u16:198",
      "u16:0",
      "u32:0",
      "u8:0",
      "a120_1c"
    ]
  },
  {
    "op": "4A",
    "offset": 2763,
    "value": [
      "bytes:19 E8 03 00"
    ]
  },
  {
    "op": "23",
    "offset": 2768,
    "value": [
      "u8:0",
      "u16:65535",
      "u16:0",
      "ele_0779.ogg"
    ]
  },
  {
    "op": "42",
    "offset": 2787,
    "value": [
      "u16:39",
      "u8:0",
      "u8:0",
      "エレナ",
      "「かわいい子ね」"
    ]
  },
  {
    "op": "8E",
    "offset": 2816,
    "value": [
      "u8:0"
    ]
  },
  {
    "op": "02",
    "offset": 2818,
    "value": [
      "u8:2",
      "u8:0",
      "u16:40",
      "エレナさんの方が、断然美人だよ",
      "u8:7",
      "ea37_3",
      "u16:41",
      "美人っていうよりかわいい方かな",
      "u8:7",
      "ea37_4"
    ]
  },
  {
    "op": "FF",
    "offset": 2903,
    "value": []
  }
]