[
  {
    "op": "8C",
    "offset": 0,
    "value": [
      "u16:146",
      "u8:0"
    ]
  },
  {
    "op": "03",
    "offset": 4,
    "value": [
      "u8:1",
      "u16:301",
      "u8:0",
      "u16:0",
      "u8:0"
    ]
  },
  {
    "op": "09",
    "offset": 12,
    "value": [
      "VIEW_CHK"
    ]
  },
  {
    "op": "21",
    "offset": 22,
    "value": [
      "u8:1",
      "u16:1000",
      "BGM06"
    ]
  },
  {
    "op": "49",
    "offset": 32,
    "value": [
      "u8:0",
      "u8:0",
      "u8:0"
    ]
  },
  {
    "op": "49",
    "offset": 36,
    "value": [
      "u8:1",
      "u8:0",
      "u8:0"
    ]
  },
  {
    "op": "46",
    "offset": 40,
    "value": [
      "u16:0",
      "u16:0",
      "u32:0",
      "u8:0",
      "B210"
    ]
  },
  {
    "op": "48",
    "offset": 55,
    "value": [
      "u8:1",
      "u16:224",
      "u16:0",
      "u32:0",
      "u8:0",
      "a802_00"
    ]
  },
  {
    "op": "4A",
    "offset": 74,
    "value": [
      "bytes:19 E8 03 00"
    ]
  },
  {
    "op": "42",
    "offset": 79,
    "value": [
      "u16:0",
      "u8:0",
      "u8:0",
      "親父",
      "「花丸、風丸、こっちだ。この人なんだ」"
    ]
  },
  {
    "op": "49",
    "offset": 128,
    "value": [
      "u8:0",
      "u8:0",
      "u8:0"
    ]
  },
  {
    "op": "49",
    "offset": 132,
    "value": [
      "u8:1",
      "u8:0",
      "u8:0"
    ]
  },
  {
    "op": "46",
    "offset": 136,
    "value": [
      "u16:0",
      "u16:0",
      "u32:0",
      "u8:0",
      "B210"
    ]
  },
  {
    "op": "48",
    "offset": 151,
    "value": [
      "u8:1",
      "u16:204",
      "u16:0",
      "u32:0",
      "u8:0",
      "a520_00"
    ]
  },
  {
    "op": "4A",
    "offset": 170,
    "value": [
      "bytes:19 F4 01 00"
    ]
  },
  {
    "op": "23",
    "offset": 175,
    "value": [
      "u8:0",
      "u16:65535",
      "u16:0",
      "ari_0024.ogg"
    ]
  },
  {
    "op": "42",
    "offset": 194,
    "value": [
      "u16:1",
      "u8:0",
      "u8:0",
      "ありさ",
      "「北条です。花丸くんには、もう何度か会ってるわね」"
    ]
  },
  {
    "op": "49",
    "offset": 257,
    "value": [
      "u8:0",
      "u8:0",
      "u8:0"
    ]
  },
  {
    "op": "49",
    "offset": 261,
    "value": [
      "u8:1",
      "u8:0",
      "u8:0"
    ]
  },
  {
    "op": "46",
    "offset": 265,
    "value": [
      "u16:0",
      "u16:0",
      "u32:0",
      "u8:0",
      "B210"
    ]
  },
  {
    "op": "48",
    "offset": 280,
    "value": [
      "u8:1",
      "u16:208",
      "u16:0",
      "u32:0",
      "u8:0",
      "a720_00"
    ]
  },
  {
    "op": "4A",
    "offset": 299,
    "value": [
      "bytes:19 F4 01 00"
    ]
  },
  {
    "op": "42",
    "offset": 304,
    "value": [
      "u16:2",
      "u8:0",
      "u8:0",
      "風丸",
      "「……」"
    ]
  },
  {
    "op": "42",
    "offset": 323,
    "value": [
      "u16:3",
      "u8:0",
      "u8:0",
      "花丸",
      "「おい、風丸」"
    ]
  },
  {
    "op": "42",
    "offset": 348,
    "value": [
      "u16:4",
      "u8:0",
      "u8:0",
      "風丸",
      "「こんにちは……」"
    ]
  },
  {
    "op": "49",
    "offset": 377,
    "value": [
      "u8:0",
      "u8:0",
      "u8:0"
    ]
  },
  {
    "op": "49",
    "offset": 381,
    "value": [
      "u8:1",
      "u8:0",
      "u8:0"
    ]
  },
  {
    "op": "46",
    "offset": 385,
    "value": [
      "u16:0",
      "u16:0",
      "u32:0",
      "u8:0",
      "B210"
    ]
  },
  {
    "op": "48",
    "offset": 400,
    "value": [
      "u8:1",
      "u16:204",
      "u16:0",
      "u32:0",
      "u8:0",
      "a520_00"
    ]
  },
  {
    "op": "4A",
    "offset": 419,
    "value": [
      "bytes:19 F4 01 00"
    ]
  },
  {
    "op": "23",
    "offset": 424,
    "value": [
      "u8:0",
      "u16:65535",
      "u16:0",
      "ari_0025.ogg"
    ]
  },
  {
    "op": "42",
    "offset": 443,
    "value": [
      "u16:5",
      "u8:0",
      "u8:0",
      "ありさ",
      "「こんにちは。よくご存じだと思うけど、娘のエレナです」"
    ]
  },
  {
    "op": "49",
    "offset": 510,
    "value": [
      "u8:0",
      "u8:0",
      "u8:0"
    ]
  },
  {
    "op": "49",
    "offset": 514,
    "value": [
      "u8:1",
      "u8:0",
      "u8:0"
    ]
  },
  {
    "op": "46",
    "offset": 518,
    "value": [
      "u16:0",
      "u16:0",
      "u32:0",
      "u8:0",
      "B210"
    ]
  },
  {
    "op": "48",
    "offset": 533,
    "value": [
      "u8:0",
      "u16:24",
      "u16:0",
      "u32:0",
      "u8:0",
      "a520_00"
    ]
  },
  {
    "op": "48",
    "offset": 552,
    "value": [
      "u8:1",
      "u16:367",
      "u16:0",
      "u32:0",
      "u8:0",
      "a130_1b"
    ]
  },
  {
    "op": "4A",
    "offset": 571,
    "value": [
      "bytes:19 F4 01 00"
    ]
  },
  {
    "op": "23",
    "offset": 576,
    "value": [
      "u8:0",
      "u16:65535",
      "u16:0",
      "ele_1139.ogg"
    ]
  },
  {
    "op": "42",
    "offset": 595,
    "value": [
      "u16:6",
      "u8:0",
      "u8:0",
      "エレナ",
      "「ど、どうも」"
    ]
  },
  {
    "op": "49",
    "offset": 622,
    "value": [
      "u8:0",
      "u8:0",
      "u8:0"
    ]
  },
  {
    "op": "49",
    "offset": 626,
    "value": [
      "u8:1",
      "u8:0",
      "u8:0"
    ]
  },
  {
    "op": "46",
    "offset": 630,
    "value": [
      "u16:0",
      "u16:0",
      "u32:0",
      "u8:0",
      "B210"
    ]
  },
  {
    "op": "48",
    "offset": 645,
    "value": [
      "u8:1",
      "u16:224",
      "u16:0",
      "u32:0",
      "u8:0",
      "a802_00"
    ]
  },
  {
    "op": "4A",
    "offset": 664,
    "value": [
      "bytes:19 F4 01 00"
    ]
  },
  {
    "op": "42",
    "offset": 669,
    "value": [
      "u16:7",
      "u8:0",
      "u8:0",
      "親父",
      "「初めまして、風丸と花丸の父です」"
    ]
  },
  {
    "op": "41",
    "offset": 714,
    "value": [
      "u16:8",
      "u8:0",
      "　なんだか妙な感じだ。"
    ]
  },
  {
    "op": "49",
    "offset": 741,
    "value": [
      "u8:0",
      "u8:0",
      "u8:0"
    ]
  },
  {
    "op": "49",
    "offset": 745,
    "value": [
      "u8:1",
      "u8:0",
      "u8:0"
    ]
  },
  {
    "op": "46",
    "offset": 749,
    "value": [
      "u16:0",
      "u16:0",
      "u32:0",
      "u8:0",
      "B210"
    ]
  },
  {
    "op": "48",
    "offset": 764,
    "value": [
      "u8:1",
      "u16:204",
      "u16:0",
      "u32:0",
      "u8:0",
      "a520_00"
    ]
  },
  {
    "op": "4A",
    "offset": 783,
    "value": [
      "bytes:19 F4 01 00"
    ]
  },
  {
    "op": "23",
    "offset": 788,
    "value": [
      "u8:0",
      "u16:65535",
      "u16:0",
      "ari_0026.ogg"
    ]
  },
  {
    "op": "42",
    "offset": 807,
    "value": [
      "u16:9",
      "u8:0",
      "u8:0",
      "ありさ",
      "「じゃ、行きましょうか。再婚とかそういうことはおいてお\\n　いて、おいしいもの食べに行きましょう」"
    ]
  },
  {
    "op": "49",
    "offset": 916,
    "value": [
      "u8:0",
      "u8:0",
      "u8:0"
    ]
  },
  {
    "op": "49",
    "offset": 920,
    "value": [
      "u8:1",
      "u8:0",
      "u8:0"
    ]
  },
  {
    "op": "46",
    "offset": 924,
    "value": [
      "u16:0",
      "u16:0",
      "u32:0",
      "u8:0",
      "BLACK"
    ]
  },
  {
    "op": "4A",
    "offset": 940,
    "value": [
      "bytes:19 E8 03 00"
    ]
  },
  {
    "op": "41",
    "offset": 945,
    "value": [
      "u16:10",
      "u8:0",
      "　食事は比較的和やかに進んだ。"
    ]
  },
  {
    "op": "41",
    "offset": 980,
    "value": [
      "u16:11",
      "u8:0",
      "　少なくとも、おれとエレナさんとは。ただ、一度も風丸が\\n笑わなかったのが気になった。"
    ]
  },
  {
    "op": "41",
    "offset": 1069,
    "value": [
      "u16:12",
      "u8:0",
      "　やっぱり……まだ母さんのことを気にしてるのだろうか。"
    ]
  },
  {
    "op": "41",
    "offset": 1128,
    "value": [
      "u16:13",
      "u8:0",
      "　……"
    ]
  },
  {
    "op": "21",
    "offset": 1139,
    "value": [
      "u8:0",
      "u16:0",
      "BGM14"
    ]
  },
  {
    "op": "49",
    "offset": 1149,
    "value": [
      "u8:0",
      "u8:0",
      "u8:0"
    ]
  },
  {
    "op": "49",
    "offset": 1153,
    "value": [
      "u8:1",
      "u8:0",
      "u8:0"
    ]
  },
  {
    "op": "46",
    "offset": 1157,
    "value": [
      "u16:0",
      "u16:0",
      "u32:0",
      "u8:0",
      "B003BL"
    ]
  },
  {
    "op": "48",
    "offset": 1174,
    "value": [
      "u8:0",
      "u16:42",
      "u16:0",
      "u32:0",
      "u8:0",
      "A720_00"
    ]
  },
  {
    "op": "48",
    "offset": 1193,
    "value": [
      "u8:1",
      "u16:385",
      "u16:0",
      "u32:0",
      "u8:0",
      "A802_00"
    ]
  },
  {
    "op": "4A",
    "offset": 1212,
    "value": [
      "bytes:19 E8 03 00"
    ]
  },
  {
    "op": "42",
    "offset": 1217,
    "value": [
      "u16:14",
      "u8:0",
      "u8:0",
      "親父",
      "「どうだった？　ありささんは」"
    ]
  },
  {
    "op": "42",
    "offset": 1258,
    "value": [
      "u16:15",
      "u8:0",
      "u8:0",
      "風丸",
      "「……」"
    ]
  },
  {
    "op": "42",
    "offset": 1277,
    "value": [
      "u16:16",
      "u8:0",
      "u8:0",
      "花丸",
      "「おれは別に。だいたい知ってる相手だし」"
    ]
  },
  {
    "op": "42",
    "offset": 1328,
    "value": [
      "u16:17",
      "u8:0",
      "u8:0",
      "親父",
      "「風丸は」"
    ]
  },
  {
    "op": "42",
    "offset": 1349,
    "value": [
      "u16:18",
      "u8:0",
      "u8:0",
      "風丸",
      "「……」"
    ]
  },
  {
    "op": "49",
    "offset": 1368,
    "value": [
      "u8:0",
      "u8:0",
      "u8:0"
    ]
  },
  {
    "op": "49",
    "offset": 1372,
    "value": [
      "u8:1",
      "u8:0",
      "u8:0"
    ]
  },
  {
    "op": "46",
    "offset": 1376,
    "value": [
      "u16:0",
      "u16:0",
      "u32:0",
      "u8:0",
      "B003BL"
    ]
  },
  {
    "op": "48",
    "offset": 1393,
    "value": [
      "u8:0",
      "u16:42",
      "u16:0",
      "u32:0",
      "u8:0",
      "A720_00"
    ]
  },
  {
    "op": "48",
    "offset": 1412,
    "value": [
      "u8:1",
      "u16:385",
      "u16:0",
      "u32:0",
      "u8:0",
      "a802_1b"
    ]
  },
  {
    "op": "4A",
    "offset": 1431,
    "value": [
      "bytes:19 F4 01 00"
    ]
  },
  {
    "op": "42",
    "offset": 1436,
    "value": [
      "u16:19",
      "u8:0",
      "u8:0",
      "親父",
      "「本当のところ、そろそろ、花丸をお役御免にしてやりたい\\n　んだ」"
    ]
  },
  {
    "op": "42",
    "offset": 1511,
    "value": [
      "u16:20",
      "u8:0",
      "u8:0",
      "親父",
      "「中学からずっと母さんの代わりをしてくれて……ずいぶん\\n　大変だったと思う。二浪したのだって多分……」"
    ]
  },
  {
    "op": "42",
    "offset": 1624,
    "value": [
      "u16:21",
      "u8:0",
      "u8:0",
      "花丸",
      "「違うよ」"
    ]
  },
  {
    "op": "42",
    "offset": 1645,
    "value": [
      "u16:22",
      "u8:0",
      "u8:0",
      "親父",
      "「でも、母さんがいれば……」"
    ]
  },
  {
    "op": "42",
    "offset": 1684,
    "value": [
      "u16:23",
      "u8:0",
      "u8:0",
      "風丸",
      "「……」"
    ]
  },
  {
    "op": "42",
    "offset": 1703,
    "value": [
      "u16:24",
      "u8:0",
      "u8:0",
      "親父",
      "「もういい加減、花丸を楽にしてやりたいんだ。もちろん、\\n　すぐ母さんなんて呼べないだろうけれど──」"
    ]
  },
  {
    "op": "42",
    "offset": 1814,
    "value": [
      "u16:25",
      "u8:0",
      "u8:0",
      "風丸",
      "「再婚するのなら好きにしたらいいと思う。おれは関係ない\\n　から」"
    ]
  },
  {
    "op": "49",
    "offset": 1889,
    "value": [
      "u8:0",
      "u8:0",
      "u8:0"
    ]
  },
  {
    "op": "49",
    "offset": 1893,
    "value": [
      "u8:1",
      "u8:0",
      "u8:0"
    ]
  },
  {
    "op": "46",
    "offset": 1897,
    "value": [
      "u16:0",
      "u16:0",
      "u32:0",
      "u8:0",
      "B003BL"
    ]
  },
  {
    "op": "48",
    "offset": 1914,
    "value": [
      "u8:0",
      "u16:42",
      "u16:0",
      "u32:0",
      "u8:0",
      "A720_00"
    ]
  },
  {
    "op": "48",
    "offset": 1933,
    "value": [
      "u8:1",
      "u16:385",
      "u16:0",
      "u32:0",
      "u8:0",
      "a802_1d"
    ]
  },
  {
    "op": "4A",
    "offset": 1952,
    "value": [
      "bytes:19 F4 01 00"
    ]
  },
  {
    "op": "42",
    "offset": 1957,
    "value": [
      "u16:26",
      "u8:0",
      "u8:0",
      "親父",
      "「風丸」"
    ]
  },
  {
    "op": "49",
    "offset": 1976,
    "value": [
      "u8:0",
      "u8:0",
      "u8:0"
    ]
  },
  {
    "op": "49",
    "offset": 1980,
    "value": [
      "u8:1",
      "u8:0",
      "u8:0"
    ]
  },
  {
    "op": "46",
    "offset": 1984,
    "value": [
      "u16:0",
      "u16:0",
      "u32:0",
      "u8:0",
      "B003BL"
    ]
  },
  {
    "op": "48",
    "offset": 2001,
    "value": [
      "u8:0",
      "u16:42",
      "u16:0",
      "u32:0",
      "u8:0",
      "A720_00"
    ]
  },
  {
    "op": "48",
    "offset": 2020,
    "value": [
      "u8:1",
      "u16:385",
      "u16:0",
      "u32:0",
      "u8:0",
      "a802_1b"
    ]
  },
  {
    "op": "4A",
    "offset": 2039,
    "value": [
      "bytes:19 F4 01 00"
    ]
  },
  {
    "op": "42",
    "offset": 2044,
    "value": [
      "u16:27",
      "u8:0",
      "u8:0",
      "親父",
      "「……」"
    ]
  },
  {
    "op": "42",
    "offset": 2063,
    "value": [
      "u16:28",
      "u8:0",
      "u8:0",
      "親父",
      "「やっぱり……駄目か……」"
    ]
  },
  {
    "op": "42",
    "offset": 2100,
    "value": [
      "u16:29",
      "u8:0",
      "u8:0",
      "花丸",
      "「……」"
    ]
  },
  {
    "op": "42",
    "offset": 2119,
    "value": [
      "u16:30",
      "u8:0",
      "u8:0",
      "親父",
      "「早く……おまえを楽にしてやりたかったのにな……」"
    ]
  },
  {
    "op": "42",
    "offset": 2180,
    "value": [
      "u16:31",
      "u8:0",
      "u8:0",
      "花丸",
      "「……」"
    ]
  },
  {
    "op": "49",
    "offset": 2199,
    "value": [
      "u8:0",
      "u8:0",
      "u8:0"
    ]
  },
  {
    "op": "49",
    "offset": 2203,
    "value": [
      "u8:1",
      "u8:0",
      "u8:0"
    ]
  },
  {
    "op": "46",
    "offset": 2207,
    "value": [
      "u16:0",
      "u16:0",
      "u32:0",
      "u8:0",
      "BLACK"
    ]
  },
  {
    "op": "4A",
    "offset": 2223,
    "value": [
      "bytes:19 E8 03 00"
    ]
  },
  {
    "op": "49",
    "offset": 2228,
    "value": [
      "u8:0",
      "u8:0",
      "u8:0"
    ]
  },
  {
    "op": "49",
    "offset": 2232,
    "value": [
      "u8:1",
      "u8:0",
      "u8:0"
    ]
  },
  {
    "op": "46",
    "offset": 2236,
    "value": [
      "u16:0",
      "u16:0",
      "u32:0",
      "u8:0",
      "B008BL"
    ]
  },
  {
    "op": "4A",
    "offset": 2253,
    "value": [
      "bytes:19 E8 03 00"
    ]
  },
  {
    "op": "41",
    "offset": 2258,
    "value": [
      "u16:32",
      "u8:0",
      "　部屋に上がってから、エレナさんと電話で話をした。"
    ]
  },
  {
    "op": "41",
    "offset": 2313,
    "value": [
      "u16:33",
      "u8:0",
      "　エレナさんのママも、風丸のことを気にしていたそうだ。\\nあの子、笑わなかったわね、ともらしていたらしい。"
    ]
  },
  {
    "op": "41",
    "offset": 2422,
    "value": [
      "u16:34",
      "u8:0",
      "　再婚は駄目になっちまうのだろうか。"
    ]
  },
  {
    "op": "22",
    "offset": 2463,
    "value": [
      "u8:1",
      "u16:1000",
      "u8:0"
    ]
  },
  {
    "op": "49",
    "offset": 2468,
    "value": [
      "u8:0",
      "u8:0",
      "u8:0"
    ]
  },
  {
    "op": "49",
    "offset": 2472,
    "value": [
      "u8:1",
      "u8:0",
      "u8:0"
    ]
  },
  {
    "op": "46",
    "offset": 2476,
    "value": [
      "u16:0",
      "u16:0",
      "u32:0",
      "u8:0",
      "BLACK"
    ]
  },
  {
    "op": "4A",
    "offset": 2492,
    "value": [
      "bytes:19 E8 03 00"
    ]
  },
  {
    "op": "21",
    "offset": 2497,
    "value": [
      "u8:0",
      "u16:0",
      "BGM10"
    ]
  },
  {
    "op": "49",
    "offset": 2507,
    "value": [
      "u8:0",
      "u8:0",
      "u8:0"
    ]
  },
  {
    "op": "49",
    "offset": 2511,
    "value": [
      "u8:1",
      "u8:0",
      "u8:0"
    ]
  },
  {
    "op": "46",
    "offset": 2515,
    "value": [
      "u16:0",
      "u16:0",
      "u32:0",
      "u8:0",
      "B002"
    ]
  },
  {
    "op": "4A",
    "offset": 2530,
    "value": [
      "bytes:19 E8 03 00"
    ]
  },
  {
    "op": "41",
    "offset": 2535,
    "value": [
      "u16:35",
      "u8:0",
      "　翌朝──"
    ]
  },
  {
    "op": "49",
    "offset": 2550,
    "value": [
      "u8:0",
      "u8:0",
      "u8:0"
    ]
  },
  {
    "op": "49",
    "offset": 2554,
    "value": [
      "u8:1",
      "u8:0",
      "u8:0"
    ]
  },
  {
    "op": "46",
    "offset": 2558,
    "value": [
      "u16:0",
      "u16:0",
      "u32:0",
      "u8:0",
      "B002"
    ]
  },
  {
    "op": "48",
    "offset": 2573,
    "value": [
      "u8:1",
      "u16:208",
      "u16:0",
      "u32:0",
      "u8:0",
      "A700_00"
    ]
  },
  {
    "op": "4A",
    "offset": 2592,
    "value": [
      "bytes:19 F4 01 00"
    ]
  },
  {
    "op": "41",
    "offset": 2597,
    "value": [
      "u16:36",
      "u8:0",
      "　風丸がいつものように起きてきた。無口なのはいつもと同\\nじ。"
    ]
  },
  {
    "op": "41",
    "offset": 2662,
    "value": [
      "u16:37",
      "u8:0",
      "　ふいにあくびをした。"
    ]
  },
  {
    "op": "42",
    "offset": 2689,
    "value": [
      "u16:38",
      "u8:0",
      "u8:0",
      "花丸",
      "「昨夜、遅かったのか？」"
    ]
  },
  {
    "op": "42",
    "offset": 2724,
    "value": [
      "u16:39",
      "u8:0",
      "u8:0",
      "風丸",
      "「ん？　ああ……」"
    ]
  },
  {
    "op": "41",
    "offset": 2753,
    "value": [
      "u16:40",
      "u8:0",
      "　そう言ってまたあくびをする。"
    ]
  },
  {
    "op": "41",
    "offset": 2788,
    "value": [
      "u16:41",
      "u8:0",
      "　おれは卵をといてフライパンにぶちまける。"
    ]
  },
  {
    "op": "42",
    "offset": 2835,
    "value": [
      "u16:42",
      "u8:0",
      "u8:0",
      "風丸",
      "「北条先輩の母さんって、料理うまいのかな」"
    ]
  },
  {
    "op": "42",
    "offset": 2888,
    "value": [
      "u16:43",
      "u8:0",
      "u8:0",
      "花丸",
      "「うまいんじゃないの？　エレナさんも上手だし」"
    ]
  },
  {
    "op": "42",
    "offset": 2945,
    "value": [
      "u16:44",
      "u8:0",
      "u8:0",
      "風丸",
      "「ふうん」"
    ]
  },
  {
    "op": "49",
    "offset": 2966,
    "value": [
      "u8:0",
      "u8:0",
      "u8:0"
    ]
  },
  {
    "op": "49",
    "offset": 2970,
    "value": [
      "u8:1",
      "u8:0",
      "u8:0"
    ]
  },
  {
    "op": "46",
    "offset": 2974,
    "value": [
      "u16:0",
      "u16:0",
      "u32:0",
      "u8:0",
      "B002"
    ]
  },
  {
    "op": "4A",
    "offset": 2989,
    "value": [
      "bytes:19 F4 01 00"
    ]
  },
  {
    "op": "41",
    "offset": 2994,
    "value": [
      "u16:45",
      "u8:0",
      "　興味なさそうにテーブルに引き上げる。"
    ]
  },
  {
    "op": "41",
    "offset": 3037,
    "value": [
      "u16:46",
      "u8:0",
      "　出し巻をお皿に移して視線を転じると、風丸は新聞を読ん\\nでいた。"
    ]
  },
  {
    "op": "42",
    "offset": 3106,
    "value": [
      "u16:47",
      "u8:0",
      "u8:0",
      "風丸",
      "「おれは、別におまえの飯でもいいけど」"
    ]
  },
  {
    "op": "41",
    "offset": 3155,
    "value": [
      "u16:48",
      "u8:0",
      "　新聞に顔を隠してそんなことを言う。"
    ]
  },
  {
    "op": "42",
    "offset": 3196,
    "value": [
      "u16:49",
      "u8:0",
      "u8:0",
      "花丸",
      "「激辛にしてやろうか」"
    ]
  },
  {
    "op": "41",
    "offset": 3229,
    "value": [
      "u16:50",
      "u8:0",
      "　ちらっとこっちを見た。"
    ]
  },
  {
    "op": "42",
    "offset": 3258,
    "value": [
      "u16:51",
      "u8:0",
      "u8:0",
      "風丸",
      "「するなよ」"
    ]
  },
  {
    "op": "42",
    "offset": 3281,
    "value": [
      "u16:52",
      "u8:0",
      "u8:0",
      "花丸",
      "「赤い出し巻を作ってやろう」"
    ]
  },
  {
    "op": "41",
    "offset": 3320,
    "value": [
      "u16:53",
      "u8:0",
      "　言って卵をかきまぜる。"
    ]
  },
  {
    "op": "49",
    "offset": 3349,
    "value": [
      "u8:0",
      "u8:0",
      "u8:0"
    ]
  },
  {
    "op": "49",
    "offset": 3353,
    "value": [
      "u8:1",
      "u8:0",
      "u8:0"
    ]
  },
  {
    "op": "46",
    "offset": 3357,
    "value": [
      "u16:0",
      "u16:0",
      "u32:0",
      "u8:0",
      "B002"
    ]
  },
  {
    "op": "48",
    "offset": 3372,
    "value": [
      "u8:1",
      "u16:208",
      "u16:0",
      "u32:0",
      "u8:0",
      "A700_00"
    ]
  },
  {
    "op": "4A",
    "offset": 3391,
    "value": [
      "bytes:19 F4 01 00"
    ]
  },
  {
    "op": "42",
    "offset": 3396,
    "value": [
      "u16:54",
      "u8:0",
      "u8:0",
      "風丸",
      "「おまえ、本気で──」"
    ]
  },
  {
    "op": "49",
    "offset": 3429,
    "value": [
      "u8:0",
      "u8:0",
      "u8:0"
    ]
  },
  {
    "op": "49",
    "offset": 3433,
    "value": [
      "u8:1",
      "u8:0",
      "u8:0"
    ]
  },
  {
    "op": "46",
    "offset": 3437,
    "value": [
      "u16:0",
      "u16:0",
      "u32:0",
      "u8:0",
      "B002"
    ]
  },
  {
    "op": "48",
    "offset": 3452,
    "value": [
      "u8:1",
      "u16:208",
      "u16:0",
      "u32:0",
      "u8:0",
      "A700_1D"
    ]
  },
  {
    "op": "4A",
    "offset": 3471,
    "value": [
      "bytes:19 F4 01 00"
    ]
  },
  {
    "op": "42",
    "offset": 3476,
    "value": [
      "u16:55",
      "u8:0",
      "u8:0",
      "風丸",
      "「わっ！　赤っ！」"
    ]
  },
  {
    "op": "42",
    "offset": 3505,
    "value": [
      "u16:56",
      "u8:0",
      "u8:0",
      "花丸",
      "「うまそうだろ。からし明太子入り出し巻」"
    ]
  },
  {
    "op": "49",
    "offset": 3556,
    "value": [
      "u8:0",
      "u8:0",
      "u8:0"
    ]
  },
  {
    "op": "49",
    "offset": 3560,
    "value": [
      "u8:1",
      "u8:0",
      "u8:0"
    ]
  },
  {
    "op": "46",
    "offset": 3564,
    "value": [
      "u16:0",
      "u16:0",
      "u32:0",
      "u8:0",
      "B002"
    ]
  },
  {
    "op": "48",
    "offset": 3579,
    "value": [
      "u8:1",
      "u16:208",
      "u16:0",
      "u32:0",
      "u8:0",
      "A700_1C"
    ]
  },
  {
    "op": "4A",
    "offset": 3598,
    "value": [
      "bytes:19 F4 01 00"
    ]
  },
  {
    "op": "41",
    "offset": 3603,
    "value": [
      "u16:57",
      "u8:0",
      "　うまそう、という顔をする。"
    ]
  },
  {
    "op": "42",
    "offset": 3636,
    "value": [
      "u16:58",
      "u8:0",
      "u8:0",
      "花丸",
      "「おれが食ってやる」"
    ]
  },
  {
    "op": "42",
    "offset": 3667,
    "value": [
      "u16:59",
      "u8:0",
      "u8:0",
      "風丸",
      "「半分寄越せ」"
    ]
  },
  {
    "op": "42",
    "offset": 3692,
    "value": [
      "u16:60",
      "u8:0",
      "u8:0",
      "花丸",
      "「おまえのはこっち。黄色いやつ」"
    ]
  },
  {
    "op": "42",
    "offset": 3735,
    "value": [
      "u16:61",
      "u8:0",
      "u8:0",
      "風丸",
      "「けち」"
    ]
  },
  {
    "op": "49",
    "offset": 3754,
    "value": [
      "u8:0",
      "u8:0",
      "u8:0"
    ]
  },
  {
    "op": "49",
    "offset": 3758,
    "value": [
      "u8:1",
      "u8:0",
      "u8:0"
    ]
  },
  {
    "op": "46",
    "offset": 3762,
    "value": [
      "u16:0",
      "u16:0",
      "u32:0",
      "u8:0",
      "B002"
    ]
  },
  {
    "op": "4A",
    "offset": 3777,
    "value": [
      "bytes:19 F4 01 00"
    ]
  },
  {
    "op": "41",
    "offset": 3782,
    "value": [
      "u16:62",
      "u8:0",
      "　風丸が引き上げた。また新聞紙に顔を隠す。"
    ]
  },
  {
    "op": "41",
    "offset": 3829,
    "value": [
      "u16:63",
      "u8:0",
      "　──こんな時間も、新しい母さんが来たら失われてしまう\\nのだろうか。"
    ]
  },
  {
    "op": "22",
    "offset": 3902,
    "value": [
      "u8:1",
      "u16:1000",
      "u8:0"
    ]
  },
  {
    "op": "49",
    "offset": 3907,
    "value": [
      "u8:0",
      "u8:0",
      "u8:0"
    ]
  },
  {
    "op": "49",
    "offset": 3911,
    "value": [
      "u8:1",
      "u8:0",
      "u8:0"
    ]
  },
  {
    "op": "46",
    "offset": 3915,
    "value": [
      "u16:0",
      "u16:0",
      "u32:0",
      "u8:0",
      "BLACK"
    ]
  },
  {
    "op": "4A",
    "offset": 3931,
    "value": [
      "bytes:19 E8 03 00"
    ]
  },
  {
    "op": "07",
    "offset": 3936,
    "value": [
      "ea46"
    ]
  },
  {
    "op": "FF",
    "offset": 3942,
    "value": []
  }
]